{
  "name": "Alma Diaz",
  "age": 34,
  "address": {
    "street": "Lofla Point",
    "city": "Lomborgu",
    "state": "KY",
    "zip": "39126"
  },
  "contact": {
    "phone": "(489) 932-8408",
    "servicePhone": "800324562"
  },
  "birthday": "1984-06-26T17:50:30.448Z",
  "ip": "108.225.96.179",
  "foo": "bar",
  "profile": {
    "about": "Lireele ja itgu ihado li rido herrudhu wamujmad lafoloza matjail hapehegu wo dokobtez sowfi sig roltal jacoeha uliko. Wi jot iri suw ka vortep itufe ladumkeh hazlipfi nire dumoc jirzuda sarodcij ibrohud novip ecano kuhhad aneolu. Ivfod katoh jac dimpi hal ovaza nuun ichi pagiwmo fu wezzasket na ikiso bu vup pihesge rutejva. Edhejo senweji eg ragjar zelimjaz wovis vu zagfilmus ne zov dopalona sefi. Favoara lip ot tuale wenom ukzo omfimid herozli zavcas bamragsi pal siloba vat wi hazkege esul se ob.",
    "bio": "Ta vejfeze redta nizijzu fojiwim bitkum zancolta fireb parol opo di humsaare noh zofide socda. Nezodjo sewva hov binujtud hev tozvaswe kifbohgef kuchidhu rewutse mid gaji hogca tebvati. Vibkuzu nus huto kijfag holkemce lemuj hesafi nej taife nopzu rokkop zev tiaso fervonu vosbe. Lot hovkosol bav emlihker vullosbeg mi fagna kocak paco sitkezo poakoog ak nedet zoz kavsicsij fewzele ushoike ipde. Te ha gu dimurga vibrefiz sec erhucboc fomvobe lugrovge bip ra vuzvusmur deveh ilmisul. Suz oc er feidati zi pukov genpucab durmep cahev do za pitutodo vambedi bo re. Ebnal kogduz hehgidtu ga wu dawgah tu teezadi suos cowas uti tunore ovupeftot gawezle."
  },
  "apiKey": "663844ae79526d5838ae39e646267ec04f7732e9ba46775b824a3c80da655d36",
  "currency": {
    "code": "AWG",
    "name": "Aruba Guilder"
  }
}